tinyprint/__init__.py
tinyprint/__main__.py
tinyprint/config.py
tinyprint/job.py
tinyprint/jobconfig.py
tinyprint/patches.py
tinyprint/preprocessor.py
tinyprint/xescpos.py
tinyprint-0.2.0.dist-info/licenses/LICENSE
tinyprint-0.2.0.dist-info/METADATA
tinyprint-0.2.0.dist-info/WHEEL
tinyprint-0.2.0.dist-info/entry_points.txt
tinyprint-0.2.0.dist-info/top_level.txt
tinyprint-0.2.0.dist-info/RECORD
