Metadata-Version: 2.4
Name: tinyprint
Version: 0.2.0
Summary: ui & cli to print zines with esc/pos printer
Author-email: Levin Eric Zimmermann <levin.eric.zimmermann@posteo.eu>
License: GPL
Requires-Python: >=3.10
License-File: LICENSE
Requires-Dist: python-escpos>=3.1
Requires-Dist: dataclasses-json>=0.6.0
Requires-Dist: marko>=2.1.2
Requires-Dist: pdf2image>=1.17.0
Provides-Extra: dev
Requires-Dist: pytest; extra == "dev"
Requires-Dist: mypy; extra == "dev"
Requires-Dist: types-six; extra == "dev"
Requires-Dist: types-pillow; extra == "dev"
Dynamic: license-file
